perspective/__init__.py
perspective/perspective.pyd
perspective/extension/finos-perspective-nbextension.json
perspective/handlers/__init__.py
perspective/handlers/aiohttp.py
perspective/handlers/starlette.py
perspective/handlers/tornado.py
perspective/templates/exported_widget.html.template
perspective/tests/__init__.py
perspective/tests/conftest.py
perspective/tests/test_dependencies.py
perspective/tests/async/test_async_client.py
perspective/tests/async/test_websocket_client.py
perspective/tests/core/__init__.py
perspective/tests/core/test_async.py
perspective/tests/multi_threaded/__init__.py
perspective/tests/multi_threaded/test_multi_threaded.py
perspective/tests/server/__init__.py
perspective/tests/server/test_server.py
perspective/tests/server/test_session.py
perspective/tests/table/__init__.py
perspective/tests/table/object_sequence.py
perspective/tests/table/test_column_paths.py
perspective/tests/table/test_delete.py
perspective/tests/table/test_exception.py
perspective/tests/table/test_leaks.py
perspective/tests/table/test_ports.py
perspective/tests/table/test_remove.py
perspective/tests/table/test_table.py
perspective/tests/table/test_table_arrow.py
perspective/tests/table/test_table_datetime.py
perspective/tests/table/test_table_infer.py
perspective/tests/table/test_table_limit.py
perspective/tests/table/test_table_numpy.py
perspective/tests/table/test_table_pandas.py
perspective/tests/table/test_table_polars.py
perspective/tests/table/test_to_arrow.py
perspective/tests/table/test_to_arrow_lz4.py
perspective/tests/table/test_to_format.py
perspective/tests/table/test_to_polars.py
perspective/tests/table/test_update.py
perspective/tests/table/test_update_arrow.py
perspective/tests/table/test_update_pandas.py
perspective/tests/table/test_view.py
perspective/tests/table/test_view_expression.py
perspective/tests/table/arrow/date32.arrow
perspective/tests/table/arrow/date64.arrow
perspective/tests/table/arrow/dict.arrow
perspective_python-4.0.1.dist-info/license_files/LICENSE.md
perspective_python-4.0.1.dist-info/license_files/LICENSE_THIRDPARTY_cargo.yml
perspective_python-4.0.1.dist-info/METADATA
perspective_python-4.0.1.dist-info/WHEEL
perspective_python-4.0.1.dist-info/RECORD
